EZ2.py
EZ2-0.0.5.dist-info/.ipynb_checkpoints/PKG-INFO-checkpoint
EZ2-0.0.5.dist-info/.ipynb_checkpoints/SOURCES-checkpoint.txt
EZ2-0.0.5.dist-info/.ipynb_checkpoints/dependency_links-checkpoint.txt
EZ2-0.0.5.dist-info/.ipynb_checkpoints/top_level-checkpoint.txt
EZ2-0.0.5.dist-info/LICENSE
EZ2-0.0.5.dist-info/METADATA
EZ2-0.0.5.dist-info/WHEEL
EZ2-0.0.5.dist-info/top_level.txt
EZ2-0.0.5.dist-info/RECORD
