Metadata-Version: 2.1
Name: EZ2
Version: 0.0.5
Summary: Fit a simple drift diffusion model to observed sample moments
Home-page: https://github.com/raoelg/EZ2
Author: Raoul P. P. P. Grasman
Author-email: R.P.P.P.Grasman@uva.nl
License: UNKNOWN
Platform: UNKNOWN
Classifier: Programming Language :: Python :: 3
Classifier: License :: OSI Approved :: Apache Software License
Classifier: Operating System :: OS Independent
Requires-Python: >=3.6
License-File: LICENSE
